<services>
    <service id="desktop_finder.monitor_mdl_event_template">
        <class>monitor_finder_event_template</class>
    </service>
    <service id="desktop_finder.monitor_mdl_event_receiver">
        <class>monitor_finder_event_receiver</class>
    </service>
    <service id="desktop_finder.monitor_mdl_event_notify">
        <class>monitor_finder_event_notify</class>
    </service>
    <service id="extend_filter_monitor_mdl_event_receiver">
        <class>monitor_finder_extend_filter_receiver</class>
    </service>
    <service id="extend_filter_monitor_mdl_event_notify">
        <class>monitor_finder_extend_filter_notify</class>
    </service>
    <service id="desktop_finder.monitor_mdl_event_group">
        <class>monitor_finder_event_group</class>
    </service>
</services>

